meltanolabs_target_csv/__init__.py
meltanolabs_target_csv/serialization.py
meltanolabs_target_csv/sinks.py
meltanolabs_target_csv/target.py
meltanolabs_target_csv-0.3.0.dist-info/METADATA
meltanolabs_target_csv-0.3.0.dist-info/WHEEL
meltanolabs_target_csv-0.3.0.dist-info/entry_points.txt
meltanolabs_target_csv-0.3.0.dist-info/licenses/LICENSE
meltanolabs_target_csv-0.3.0.dist-info/RECORD
