Metadata-Version: 2.4
Name: meltanolabs-target-csv
Version: 0.3.0
Summary: Singer target for CSV, built with the Meltano SDK for Singer Targets.
Author-email: Meltano <hello@meltano.com>
License-Expression: Apache-2.0
License-File: LICENSE
Keywords: CSV,ELT,ETL,Meltano,Meltano SDK,Singer
Classifier: Intended Audience :: Developers
Classifier: License :: OSI Approved :: Apache Software License
Classifier: Operating System :: OS Independent
Classifier: Programming Language :: Python :: 3.10
Classifier: Programming Language :: Python :: 3.11
Classifier: Programming Language :: Python :: 3.12
Classifier: Programming Language :: Python :: 3.13
Classifier: Programming Language :: Python :: 3.14
Classifier: Programming Language :: Python :: 3.15
Requires-Python: >=3.10
Requires-Dist: pytz~=2025.1
Requires-Dist: singer-sdk<0.54.0,>=0.50.2
